ts_protocol_virtual_machine/compiler/__init__.py
ts_protocol_virtual_machine/compiler/sources/__init__.py
ts_protocol_virtual_machine/compiler/sources/impl.py
ts_protocol_virtual_machine/compiler/transition.py
ts_protocol_virtual_machine/messages/__init__.py
ts_protocol_virtual_machine/resources/.gitignore
ts_protocol_virtual_machine/resources/compiler.js
ts_protocol_virtual_machine/result/__init__.py
ts_protocol_virtual_machine-1.9.0.dist-info/METADATA
ts_protocol_virtual_machine-1.9.0.dist-info/WHEEL
ts_protocol_virtual_machine-1.9.0.dist-info/RECORD
