Metadata-Version: 2.4
Name: ts-protocol-virtual-machine
Version: 1.9.0
Summary: tetrascience protocol compiler
License: Apache-2.0
Author: tetrascience
Requires-Python: >=3.9,<4
Classifier: License :: OSI Approved :: Apache Software License
Classifier: Programming Language :: Python :: 3
Classifier: Programming Language :: Python :: 3.9
Classifier: Programming Language :: Python :: 3.10
Classifier: Programming Language :: Python :: 3.11
Classifier: Programming Language :: Python :: 3.12
Classifier: Programming Language :: Python :: 3.13
Classifier: Programming Language :: Python :: 3.14
Requires-Dist: pythonmonkey (>=1.2.0,<2.0.0)
Project-URL: Homepage, https://developers.tetrascience.com
